CITATION.cff
LICENSE.md
MANIFEST.in
README.md
pypi_to_import
requirements.txt
setup.py
sPyNNaker8.egg-info/PKG-INFO
sPyNNaker8.egg-info/SOURCES.txt
sPyNNaker8.egg-info/dependency_links.txt
sPyNNaker8.egg-info/requires.txt
sPyNNaker8.egg-info/top_level.txt
spynnaker8/__init__.py
spynnaker8/_version.py
spynnaker8/setup_pynn.py
spynnaker8/spinnaker.py
spynnaker8/spynnaker8_simulator_interface.py
spynnaker8/spynnaker_plotting.py
spynnaker8/external_devices/__init__.py
spynnaker8/extra_models/__init__.py
spynnaker8/models/__init__.py
spynnaker8/models/data_cache.py
spynnaker8/models/projection.py
spynnaker8/models/recorder.py
spynnaker8/models/variable_cache.py
spynnaker8/models/connectors/__init__.py
spynnaker8/models/connectors/all_to_all_connector.py
spynnaker8/models/connectors/array_connector.py
spynnaker8/models/connectors/csa_connector.py
spynnaker8/models/connectors/distance_dependent_probability_connector.py
spynnaker8/models/connectors/fixed_number_post_connector.py
spynnaker8/models/connectors/fixed_number_pre_connector.py
spynnaker8/models/connectors/fixed_probability_connector.py
spynnaker8/models/connectors/from_file_connector.py
spynnaker8/models/connectors/from_list_connector.py
spynnaker8/models/connectors/index_based_probability_connector.py
spynnaker8/models/connectors/kernel_connector.py
spynnaker8/models/connectors/multapse_connector.py
spynnaker8/models/connectors/one_to_one_connector.py
spynnaker8/models/connectors/small_world_connector.py
spynnaker8/models/populations/__init__.py
spynnaker8/models/populations/assembly.py
spynnaker8/models/populations/idmixin.py
spynnaker8/models/populations/population.py
spynnaker8/models/populations/population_base.py
spynnaker8/models/populations/population_view.py
spynnaker8/models/synapse_dynamics/__init__.py
spynnaker8/models/synapse_dynamics/synapse_dynamics_static.py
spynnaker8/models/synapse_dynamics/synapse_dynamics_stdp.py
spynnaker8/models/synapse_dynamics/synapse_dynamics_structural_static.py
spynnaker8/models/synapse_dynamics/synapse_dynamics_structural_stdp.py
spynnaker8/models/synapse_dynamics/timing_dependence/__init__.py
