Metadata-Version: 1.2
Name: sPyNNaker8
Version: 1!5.1.0
Summary: Tools for simulating neural models generated using PyNN 0.9 on the SpiNNaker platform
Home-page: https://github.com/SpiNNakerManchester/SpyNNaker8
Author: University of Manchester
Maintainer: SpiNNakerTeam
Maintainer-email: spinnakerusers@googlegroups.com
License: UNKNOWN
Keywords: spinnaker pynn0.9 neural simulation
Platform: UNKNOWN
Classifier: Development Status :: 3 - Alpha
Classifier: Intended Audience :: Developers
Classifier: Intended Audience :: Science/Research
Classifier: License :: OSI Approved :: GNU General Public License v2 (GPLv2)
Classifier: Natural Language :: English
Classifier: Operating System :: POSIX :: Linux
Classifier: Operating System :: Microsoft :: Windows
Classifier: Operating System :: MacOS
Classifier: Programming Language :: Python :: 3
Classifier: Programming Language :: Python :: 3.5
Classifier: Programming Language :: Python :: 3.6
Classifier: Programming Language :: Python :: 3.7
